[
  {
    "accountId": "njnu-main",
    "title": "GLOBAL: 这个班级的\"硬核\"密码！",
    "publishDate": "2026-03-16",
    "readCount": 16000,
    "likeCount": 112
  },
  {
    "accountId": "njnu-main",
    "title": "南京师范大学2026年专业技术人员招聘公告",
    "publishDate": "2026-03-15",
    "readCount": 31000,
    "likeCount": 124
  },
  {
    "accountId": "njnu-main",
    "title": "南师大部署开展树立和践行正确政绩观学习教育",
    "publishDate": "2026-03-13",
    "readCount": 3983,
    "likeCount": 40
  },
  {
    "accountId": "njnu-main",
    "title": "吴为山校友在全国政协十四届四次会议第三次全体会议上作大会发言",
    "publishDate": "2026-03-12",
    "readCount": 9300,
    "likeCount": 70
  },
  {
    "accountId": "njnu-main",
    "title": "春启新程，不负韶华（内附考试安排）",
    "publishDate": "2026-03-11",
    "readCount": 18000,
    "likeCount": 225
  },
  {
    "accountId": "njnu-main",
    "title": "当你翻开一本春天的书……",
    "publishDate": "2026-03-10",
    "readCount": 4180,
    "likeCount": 141
  },
  {
    "accountId": "njnu-main",
    "title": "全国奖项+2！原来传统文化可以这么\"潮\"！",
    "publishDate": "2026-03-09",
    "readCount": 8831,
    "likeCount": 109
  },
  {
    "accountId": "njnu-main",
    "title": "春风沐巾帼，芳华绕南师（文末有礼）",
    "publishDate": "2026-03-07",
    "readCount": 6235,
    "likeCount": 85
  },
  {
    "accountId": "njnu-main",
    "title": "何思澹：步履不停，山海可越",
    "publishDate": "2026-03-06",
    "readCount": 15000,
    "likeCount": 161
  },
  {
    "accountId": "njnu-main",
    "title": "@毕业生 安心留南京",
    "publishDate": "2026-03-05",
    "readCount": 28000,
    "likeCount": 205
  },
  {
    "accountId": "njnu-main",
    "title": "马上焕新！南师专属校历、计划表、壁纸，送你！",
    "publishDate": "2026-03-04",
    "readCount": 8601,
    "likeCount": 229
  },
  {
    "accountId": "njnu-main",
    "title": "校领导检查新学期第一课",
    "publishDate": "2026-03-03",
    "readCount": 13000,
    "likeCount": 89
  },
  {
    "accountId": "njnu-main",
    "title": "当你翻开一本春天的书......",
    "publishDate": "2026-03-10",
    "readCount": 4180,
    "likeCount": 141
  },
  {
    "accountId": "njnu-main",
    "title": "全国奖项+2！原来传统文化可以这么\"潮\"!",
    "publishDate": "2026-03-09",
    "readCount": 8831,
    "likeCount": 109
  },
  {
    "accountId": "njnu-main",
    "title": "这个寒假，南师学子去哪了？",
    "publishDate": "2026-03-02",
    "readCount": 15000,
    "likeCount": 195
  },
  {
    "accountId": "njnu-main",
    "title": "实干笃行！2026年，南师这么干！",
    "publishDate": "2026-03-01",
    "readCount": 9546,
    "likeCount": 64
  },
  {
    "accountId": "njnu-main",
    "title": "南师大2026年硕士研究生招生考试初试成绩即将公布！",
    "publishDate": "2026-02-28",
    "readCount": 34000,
    "likeCount": 213
  },
  {
    "accountId": "njnu-main",
    "title": "开足马力！南师\"新春第一会\"召开",
    "publishDate": "2026-02-26",
    "readCount": 12000,
    "likeCount": 102
  },
  {
    "accountId": "njnu-main",
    "title": "点击开启，手到福来！",
    "publishDate": "2026-02-23",
    "readCount": 6627,
    "likeCount": 175
  },
  {
    "accountId": "njnu-main",
    "title": "南师红包封面🧧，马上返场！",
    "publishDate": "2026-02-21",
    "readCount": 9898,
    "likeCount": 169
  },
  {
    "accountId": "njnu-main",
    "title": "\"马\"上有福！快来抽取南师好运签",
    "publishDate": "2026-02-19",
    "readCount": 5423,
    "likeCount": 167
  },
  {
    "accountId": "njnu-main",
    "title": "拜年啦！南师祝您马年大吉！",
    "publishDate": "2026-02-17",
    "readCount": 1133,
    "likeCount": 44
  },
  {
    "accountId": "njnu-main",
    "title": "马上领🧧！南师红包封面来啦",
    "publishDate": "2026-02-16",
    "readCount": 19000,
    "likeCount": 477
  },
  {
    "accountId": "njnu-main",
    "title": "当南师遇上拼豆......",
    "publishDate": "2026-02-13",
    "readCount": 21000,
    "likeCount": 384
  },
  {
    "accountId": "njnu-main",
    "title": "校领导开展春节前走访慰问",
    "publishDate": "2026-02-11",
    "readCount": 11000,
    "likeCount": 86
  },
  {
    "accountId": "njnu-main",
    "title": "张一桐：安静生长，终成青绿",
    "publishDate": "2026-02-10",
    "readCount": 10000,
    "likeCount": 98
  },
  {
    "accountId": "njnu-main",
    "title": "南京师范大学 2026年非教学单位工作人员（人事代理）招聘公告",
    "publishDate": "2026-02-08",
    "readCount": 37000,
    "likeCount": 175
  },
  {
    "accountId": "njnu-main",
    "title": "我校政协委员在省\"两会\"上积极履职建言",
    "publishDate": "2026-02-06",
    "readCount": 4784,
    "likeCount": 61
  },
  {
    "accountId": "njnu-main",
    "title": "邓雨欣：\"氨\"舟已过万重山",
    "publishDate": "2026-02-05",
    "readCount": 22000,
    "likeCount": 214
  },
  {
    "accountId": "njnu-main",
    "title": "南师教授团队第八部国际专著全球发行",
    "publishDate": "2026-02-03",
    "readCount": 6040,
    "likeCount": 64
  },
  {
    "accountId": "njnu-main",
    "title": "\"冷门绝学\"，南师获批！",
    "publishDate": "2026-02-01",
    "readCount": 44000,
    "likeCount": 360
  },
  {
    "accountId": "njnu-main",
    "title": "祝贺！获奖16项",
    "publishDate": "2026-01-30",
    "readCount": 11000,
    "likeCount": 100
  },
  {
    "accountId": "njnu-main",
    "title": "榜样！他们是优秀研究生标兵",
    "publishDate": "2026-01-28",
    "readCount": 20000,
    "likeCount": 154
  },
  {
    "accountId": "njnu-main",
    "title": "郁贤皓先生的学术贡献与治学方法",
    "publishDate": "2026-01-26",
    "readCount": 3429,
    "likeCount": 92
  },
  {
    "accountId": "njnu-main",
    "title": "倒计时3天！2026国际青年学者论坛即将开幕",
    "publishDate": "2026-01-24",
    "readCount": 2969,
    "likeCount": 18
  },
  {
    "accountId": "njnu-main",
    "title": "招贤纳才 南师等您丨一封来自南京师范大学的博士后进站邀请函",
    "publishDate": "2026-01-24",
    "readCount": 8671,
    "likeCount": 39
  },
  {
    "accountId": "njnu-main",
    "title": "致敬！他们在南师光荣退休",
    "publishDate": "2026-01-22",
    "readCount": 22000,
    "likeCount": 176
  },
  {
    "accountId": "njnu-main",
    "title": "寒假指南，请查收!",
    "publishDate": "2026-01-21",
    "readCount": 14000,
    "likeCount": 96
  },
  {
    "accountId": "njnu-main",
    "title": "太会了！原来你的专业能取暖😋",
    "publishDate": "2026-01-19",
    "readCount": 12000,
    "likeCount": 215
  },
  {
    "accountId": "njnu-main",
    "title": "周琳欣：南师大→中科院，用奋斗书写科研答卷",
    "publishDate": "2026-01-18",
    "readCount": 21000,
    "likeCount": 244
  },
  {
    "accountId": "njnu-main",
    "title": "南师大，Nature再+1！",
    "publishDate": "2026-01-16",
    "readCount": 30000,
    "likeCount": 351
  },
  {
    "accountId": "njnu-main",
    "title": "温馨提醒：明天报名截止！",
    "publishDate": "2026-01-15",
    "readCount": 5939,
    "likeCount": 35
  },
  {
    "accountId": "njnu-main",
    "title": "期末周，吃点啥？",
    "publishDate": "2026-01-14",
    "readCount": 11000,
    "likeCount": 141
  },
  {
    "accountId": "njnu-main",
    "title": "南师校友—世界冠军—\"中国好人\"",
    "publishDate": "2026-01-13",
    "readCount": 6869,
    "likeCount": 101
  },
  {
    "accountId": "njnu-main",
    "title": "刘雅坤：解锁\"不适合\"里的无限可能",
    "publishDate": "2026-01-12",
    "readCount": 6901,
    "likeCount": 135
  },
  {
    "accountId": "njnu-main",
    "title": "NNUers冬日歌单，哪首是你的\"心头好\"?",
    "publishDate": "2026-01-11",
    "readCount": 6054,
    "likeCount": 118
  },
  {
    "accountId": "njnu-main",
    "title": "新春游园会，策马奔来！",
    "publishDate": "2026-01-09",
    "readCount": 7157,
    "likeCount": 70
  },
  {
    "accountId": "njnu-main",
    "title": "听，南师校园声景～",
    "publishDate": "2026-01-08",
    "readCount": 4783,
    "likeCount": 80
  },
  {
    "accountId": "njnu-main",
    "title": "超越\"三点一线\"，定义你的第N空间",
    "publishDate": "2026-01-07",
    "readCount": 3785,
    "likeCount": 69
  },
  {
    "accountId": "njnu-main",
    "title": "陈超杰：从\"压线\"进校到直博上岸",
    "publishDate": "2026-01-06",
    "readCount": 22000,
    "likeCount": 179
  },
  {
    "accountId": "njnu-main",
    "title": "上新！南师2026月历（文末有惊喜）",
    "publishDate": "2026-01-04",
    "readCount": 22000,
    "likeCount": 768
  },
  {
    "accountId": "njnu-main",
    "title": "2025年度南京师范大学高质量发展十件大事",
    "publishDate": "2026-01-02",
    "readCount": 11000,
    "likeCount": 135
  },
  {
    "accountId": "njnu-main",
    "title": "同心筑梦 奋进一流｜南京师范大学2026年新年贺词",
    "publishDate": "2026-01-01",
    "readCount": 7088,
    "likeCount": 201
  },
  {
    "accountId": "njnu-main",
    "title": "厚生情，南师梦｜南京师范大学举行2026年新年联欢会",
    "publishDate": "2025-12-31",
    "readCount": 12000,
    "likeCount": 238
  },
  {
    "accountId": "njnu-main",
    "title": "节目单来了！就在今天14:00",
    "publishDate": "2025-12-30",
    "readCount": 20000,
    "likeCount": 181
  },
  {
    "accountId": "njnu-main",
    "title": "南师2025年\"优秀辅导员奖\"风采展评",
    "publishDate": "2025-12-29",
    "readCount": 38000,
    "likeCount": 275
  },
  {
    "accountId": "njnu-main",
    "title": "南京师范大学金陵女子学院建院110周年创新发展大会举行",
    "publishDate": "2025-12-21",
    "readCount": 7478,
    "likeCount": 124
  },
  {
    "accountId": "njnu-main",
    "title": "考前须知，请查收！",
    "publishDate": "2025-12-19",
    "readCount": 16000,
    "likeCount": 99
  },
  {
    "accountId": "njnu-main",
    "title": "南师\"十佳示范班级\"，揭晓！",
    "publishDate": "2025-12-18",
    "readCount": 20000,
    "likeCount": 213
  },
  {
    "accountId": "njnu-main",
    "title": "\"稳\"住，我们能赢！",
    "publishDate": "2025-12-17",
    "readCount": 10000,
    "likeCount": 236
  },
  {
    "accountId": "njnu-main",
    "title": "学习空间再上新！好想上自习",
    "publishDate": "2025-12-16",
    "readCount": 10000,
    "likeCount": 158
  },
  {
    "accountId": "njnu-main",
    "title": "这位南师学子，用热血为生命接力！",
    "publishDate": "2025-12-15",
    "readCount": 11000,
    "likeCount": 178
  },
  {
    "accountId": "njnu-main",
    "title": "88年，我们从未忘记！",
    "publishDate": "2025-12-13",
    "readCount": 8312,
    "likeCount": 464
  },
  {
    "accountId": "njnu-main",
    "title": "南师冬日\"皮肤\"上新！",
    "publishDate": "2025-12-12",
    "readCount": 7858,
    "likeCount": 140
  },
  {
    "accountId": "njnu-main",
    "title": "薄千智：把论文写在田野的\"蜻蜓队长\"",
    "publishDate": "2025-12-11",
    "readCount": 6601,
    "likeCount": 123
  },
  {
    "accountId": "njnu-main",
    "title": "10天！上岸南师！",
    "publishDate": "2025-12-10",
    "readCount": 20000,
    "likeCount": 476
  },
  {
    "accountId": "njnu-main",
    "title": "漫步随园，仰望檐角的秘密",
    "publishDate": "2025-12-09",
    "readCount": 5812,
    "likeCount": 170
  },
  {
    "accountId": "njnu-main",
    "title": "南京师范大学2026年博士研究生招生章程",
    "publishDate": "2025-12-08",
    "readCount": 32000,
    "likeCount": 145
  },
  {
    "accountId": "njnu-main",
    "title": "活力南师，向阳奔跑！",
    "publishDate": "2025-12-07",
    "readCount": 12000,
    "likeCount": 226
  },
  {
    "accountId": "njnu-main",
    "title": "再见，纸车票；你好，旧时光！",
    "publishDate": "2025-12-05",
    "readCount": 7792,
    "likeCount": 151
  },
  {
    "accountId": "njnu-main",
    "title": "南师大易凯教授领衔CMS联合团队在Nature发表最新研究成果",
    "publishDate": "2025-12-04",
    "readCount": 8560,
    "likeCount": 113
  },
  {
    "accountId": "njnu-main",
    "title": "喜欢南师的他们，也喜欢这些书",
    "publishDate": "2025-12-03",
    "readCount": 6713,
    "likeCount": 112
  },
  {
    "accountId": "njnu-main",
    "title": "谷麦闻：国旗之下，青春无悔",
    "publishDate": "2025-12-02",
    "readCount": 6678,
    "likeCount": 160
  },
  {
    "accountId": "njnu-main",
    "title": "十二月，送你一份小\"杏\"运~",
    "publishDate": "2025-12-01",
    "readCount": 8021,
    "likeCount": 171
  },
  {
    "accountId": "njnu-main",
    "title": "独立\"PI\"+专属平台｜南京师范大学海外英才恳谈会诚邀您来！",
    "publishDate": "2025-11-30",
    "readCount": 5983,
    "likeCount": 47
  },
  {
    "accountId": "njnu-main",
    "title": "南师大举行学习贯彻党的二十届四中全会精神省委宣讲团报告会",
    "publishDate": "2025-11-28",
    "readCount": 4052,
    "likeCount": 30
  },
  {
    "accountId": "njnu-main",
    "title": "优秀是期许，完整是答案",
    "publishDate": "2025-11-27",
    "readCount": 13000,
    "likeCount": 485
  },
  {
    "accountId": "njnu-main",
    "title": "西班牙·马德里｜南京师范大学2025全球人才推介会",
    "publishDate": "2025-11-26",
    "readCount": 9378,
    "likeCount": 62
  },
  {
    "accountId": "njnu-main",
    "title": "百团大\"绽\"｜解锁你的N种可能！",
    "publishDate": "2025-11-25",
    "readCount": 7000,
    "likeCount": 103
  },
  {
    "accountId": "njnu-main",
    "title": "听！他们的科研成长故事",
    "publishDate": "2025-11-24",
    "readCount": 16000,
    "likeCount": 129
  },
  {
    "accountId": "njnu-main",
    "title": "伍瑞：在昆虫世界探索生命奥秘",
    "publishDate": "2025-11-23",
    "readCount": 2749,
    "likeCount": 69
  },
  {
    "accountId": "njnu-main",
    "title": "多问问，又能怎？😕",
    "publishDate": "2025-11-21",
    "readCount": 10000,
    "likeCount": 249
  },
  {
    "accountId": "njnu-main",
    "title": "全运会江苏女排夺冠！其中多名队员来自南师大",
    "publishDate": "2025-11-20",
    "readCount": 10000,
    "likeCount": 241
  },
  {
    "accountId": "njnu-main",
    "title": "\"辞家千里又千里，务必争气再争气\"",
    "publishDate": "2025-11-19",
    "readCount": 26000,
    "likeCount": 519
  },
  {
    "accountId": "njnu-main",
    "title": "南师壁纸｜把校园的诗与光，藏进你的屏幕",
    "publishDate": "2025-11-18",
    "readCount": 6502,
    "likeCount": 165
  },
  {
    "accountId": "njnu-main",
    "title": "张子旭：用智能之笔绘就青春华章",
    "publishDate": "2025-11-17",
    "readCount": 7472,
    "likeCount": 78
  },
  {
    "accountId": "njnu-main",
    "title": "三十而立｜南师大出版社，生日快乐！",
    "publishDate": "2025-11-15",
    "readCount": 10000,
    "likeCount": 170
  },
  {
    "accountId": "njnu-main",
    "title": "15个！南师大微生物学跻身ESI全球前1%",
    "publishDate": "2025-11-14",
    "readCount": 10000,
    "likeCount": 115
  },
  {
    "accountId": "njnu-main",
    "title": "今天，你\"搭子\"社交了吗？",
    "publishDate": "2025-11-13",
    "readCount": 11000,
    "likeCount": 182
  },
  {
    "accountId": "njnu-main",
    "title": "江苏省委常委、南京市委书记周红波在南师宣讲党的二十届四中全会精神并调研",
    "publishDate": "2025-11-12",
    "readCount": 12000,
    "likeCount": 93
  },
  {
    "accountId": "njnu-main",
    "title": "他们，用代码编织梦想",
    "publishDate": "2025-11-11",
    "readCount": 9724,
    "likeCount": 124
  },
  {
    "accountId": "njnu-main",
    "title": "大师背影｜吴贻芳先生：秉厚生为国，贻馥都芬芳",
    "publishDate": "2025-11-10",
    "readCount": 3435,
    "likeCount": 127
  },
  {
    "accountId": "njnu-main",
    "title": "钟伯坚：责任·热爱·传承",
    "publishDate": "2025-11-09",
    "readCount": 5322,
    "likeCount": 100
  },
  {
    "accountId": "njnu-main",
    "title": "南师大⇌盐城市，深化合作再谱新篇！",
    "publishDate": "2025-11-07",
    "readCount": 10000,
    "likeCount": 102
  },
  {
    "accountId": "njnu-main",
    "title": "干了这碗\"丝瓜汤\"！",
    "publishDate": "2025-11-06",
    "readCount": 12000,
    "likeCount": 237
  },
  {
    "accountId": "njnu-main",
    "title": "特等奖4项！我校在第十九届\"挑战杯\"全国大学生课外学术科技作品竞赛中获佳绩",
    "publishDate": "2025-11-05",
    "readCount": 13000,
    "likeCount": 170
  },
  {
    "accountId": "njnu-main",
    "title": "郭原源：科技暖阳，以智慧创新书写人文关怀",
    "publishDate": "2025-11-04",
    "readCount": 5333,
    "likeCount": 66
  },
  {
    "accountId": "njnu-main",
    "title": "打卡！南师再添\"新地标\"",
    "publishDate": "2025-11-03",
    "readCount": 43000,
    "likeCount": 586
  },
  {
    "accountId": "njnu-main",
    "title": "百十荣光，再创南师体育事业新辉煌！",
    "publishDate": "2025-11-02",
    "readCount": 11000,
    "likeCount": 165
  },
  {
    "accountId": "njnu-main",
    "title": "桂香初起，秋临南师",
    "publishDate": "2025-10-31",
    "readCount": 10000,
    "likeCount": 270
  },
  {
    "accountId": "njnu-main",
    "title": "\"万人说新疆\"分享会走进南师",
    "publishDate": "2025-10-30",
    "readCount": 5276,
    "likeCount": 78
  },
  {
    "accountId": "njnu-main",
    "title": "在南师，许你一生浪漫",
    "publishDate": "2025-10-29",
    "readCount": 47000,
    "likeCount": 1658
  },
  {
    "accountId": "njnu-main",
    "title": "万人说新疆｜就在明天，南师邀你共赴一场天山奇遇！",
    "publishDate": "2025-10-28",
    "readCount": 6700,
    "likeCount": 62
  },
  {
    "accountId": "njnu-main",
    "title": "报名即将截止，敬请关注！",
    "publishDate": "2025-10-27",
    "readCount": 20000,
    "likeCount": 63
  },
  {
    "accountId": "njnu-main",
    "title": "南师\"食\"光，美好\"味\"来",
    "publishDate": "2025-10-26",
    "readCount": 10000,
    "likeCount": 141
  },
  {
    "accountId": "njnu-main",
    "title": "南师运动会，开幕！",
    "publishDate": "2025-10-24",
    "readCount": 20000,
    "likeCount": 417
  },
  {
    "accountId": "njnu-main",
    "title": "原来你是这YOUNG的主理人",
    "publishDate": "2025-10-23",
    "readCount": 9311,
    "likeCount": 113
  },
  {
    "accountId": "njnu-main",
    "title": "在南师，翻越属于自己的\"浪浪山\"",
    "publishDate": "2025-10-22",
    "readCount": 9887,
    "likeCount": 199
  },
  {
    "accountId": "njnu-main",
    "title": "严月：以体育为炬，用脚步丈量初心与梦想",
    "publishDate": "2025-10-21",
    "readCount": 7320,
    "likeCount": 134
  },
  {
    "accountId": "njnu-main",
    "title": "南师表情包上新啦！",
    "publishDate": "2025-10-20",
    "readCount": 14000,
    "likeCount": 171
  },
  {
    "accountId": "njnu-main",
    "title": "秋风起，来南师赴一场诗意之约",
    "publishDate": "2025-10-19",
    "readCount": 8669,
    "likeCount": 151
  },
  {
    "accountId": "njnu-main",
    "title": "见义勇为！陈睿思，好样的！",
    "publishDate": "2025-10-17",
    "readCount": 29000,
    "likeCount": 982
  },
  {
    "accountId": "njnu-main",
    "title": "南师大33个学科上榜中国最好学科",
    "publishDate": "2025-10-16",
    "readCount": 30000,
    "likeCount": 388
  },
  {
    "accountId": "njnu-main",
    "title": "当星露谷农夫开始搞学术......",
    "publishDate": "2025-10-15",
    "readCount": 24000,
    "likeCount": 1043
  },
  {
    "accountId": "njnu-main",
    "title": "\"双双\"南师，双倍精彩",
    "publishDate": "2025-10-14",
    "readCount": 13000,
    "likeCount": 133
  },
  {
    "accountId": "njnu-main",
    "title": "南师九宫格，每个瞬间都精彩",
    "publishDate": "2025-10-13",
    "readCount": 8936,
    "likeCount": 100
  },
  {
    "accountId": "njnu-main",
    "title": "第一作者！Nature+1！",
    "publishDate": "2025-10-11",
    "readCount": 34000,
    "likeCount": 328
  },
  {
    "accountId": "njnu-main",
    "title": "金秋招聘，\"位\"你而来",
    "publishDate": "2025-10-10",
    "readCount": 16000,
    "likeCount": 101
  },
  {
    "accountId": "njnu-main",
    "title": "南京师范大学2026年硕士研究生招生章程",
    "publishDate": "2025-10-09",
    "readCount": 36000,
    "likeCount": 325
  },
  {
    "accountId": "njnu-main",
    "title": "银龄生辉：孙志人教授的援疆情缘",
    "publishDate": "2025-10-07",
    "readCount": 9835,
    "likeCount": 251
  },
  {
    "accountId": "njnu-main",
    "title": "今夜，我们收集人间散落的光",
    "publishDate": "2025-10-06",
    "readCount": 4815,
    "likeCount": 226
  },
  {
    "accountId": "njnu-main",
    "title": "亲手制作的南师月饼，送你！",
    "publishDate": "2025-10-05",
    "readCount": 12000,
    "likeCount": 151
  },
  {
    "accountId": "njnu-main",
    "title": "上榜！2家智库入选2025年AMI智库名单",
    "publishDate": "2025-10-03",
    "readCount": 4840,
    "likeCount": 48
  },
  {
    "accountId": "njnu-main",
    "title": "祝贺！立项数再创新高",
    "publishDate": "2025-10-02",
    "readCount": 17000,
    "likeCount": 206
  },
  {
    "accountId": "njnu-main",
    "title": "祝福祖国！南师大师生代表在天安门观礼国庆升旗仪式",
    "publishDate": "2025-10-01",
    "readCount": 22000,
    "likeCount": 442
  },
  {
    "accountId": "njnu-main",
    "title": "今天，致敬人民英雄！",
    "publishDate": "2025-09-30",
    "readCount": 3093,
    "likeCount": 92
  },
  {
    "accountId": "njnu-main",
    "title": "南师美食指南，跟着吃就对了！",
    "publishDate": "2025-09-29",
    "readCount": 13000,
    "likeCount": 157
  },
  {
    "accountId": "njnu-main",
    "title": "祝贺！再创佳绩！",
    "publishDate": "2025-09-28",
    "readCount": 8492,
    "likeCount": 92
  },
  {
    "accountId": "njnu-main",
    "title": "燃，迷彩青春，收官不说再见！",
    "publishDate": "2025-09-26",
    "readCount": 16000,
    "likeCount": 298
  },
  {
    "accountId": "njnu-main",
    "title": "优秀值拉满！南师第二十届优宣团风采展",
    "publishDate": "2025-09-24",
    "readCount": 9505,
    "likeCount": 102
  },
  {
    "accountId": "njnu-main",
    "title": "免费送！当非遗遇见南师月饼",
    "publishDate": "2025-09-24",
    "readCount": 11000,
    "likeCount": 619
  },
  {
    "accountId": "njnu-main",
    "title": "孙小曼：在微观世界\"造物\"",
    "publishDate": "2025-09-23",
    "readCount": 5747,
    "likeCount": 80
  },
  {
    "accountId": "njnu-main",
    "title": "悦读悦美丨南师新学期书单推荐",
    "publishDate": "2025-09-22",
    "readCount": 5091,
    "likeCount": 93
  },
  {
    "accountId": "njnu-main",
    "title": "从南师到联合国：葛欣果的\"禁毒答卷\"",
    "publishDate": "2025-09-21",
    "readCount": 8255,
    "likeCount": 130
  },
  {
    "accountId": "njnu-main",
    "title": "南师\"最美笔记\"有多美?",
    "publishDate": "2025-09-19",
    "readCount": 18000,
    "likeCount": 395
  },
  {
    "accountId": "njnu-main",
    "title": "勿忘，九一八！",
    "publishDate": "2025-09-18",
    "readCount": 4860,
    "likeCount": 168
  },
  {
    "accountId": "njnu-main",
    "title": "南师微专业，来啦!",
    "publishDate": "2025-09-17",
    "readCount": 15000,
    "likeCount": 143
  },
  {
    "accountId": "njnu-main",
    "title": "吕奕铖：以法为桥，以爱厚生",
    "publishDate": "2025-09-16",
    "readCount": 7737,
    "likeCount": 80
  },
  {
    "accountId": "njnu-main",
    "title": "一键收藏！南京师范大学2025秋季学期校历+计划表",
    "publishDate": "2025-09-15",
    "readCount": 23000,
    "likeCount": 306
  },
  {
    "accountId": "njnu-main",
    "title": "校长华桂宏在2025级本科生开学典礼上的讲话｜弘扬优良传统 勇赴时代之约",
    "publishDate": "2025-09-12",
    "readCount": 7002,
    "likeCount": 101
  },
  {
    "accountId": "njnu-main",
    "title": "校长华桂宏在2025级研究生开学典礼上的讲话｜研途问道 砺心致远",
    "publishDate": "2025-09-12",
    "readCount": 3104,
    "likeCount": 37
  },
  {
    "accountId": "njnu-main",
    "title": "省委常委、省委宣传部部长徐缨到南京师范大学讲授思政课",
    "publishDate": "2025-09-11",
    "readCount": 12000,
    "likeCount": 67
  },
  {
    "accountId": "njnu-main",
    "title": "扬帆起航新征途！南京师范大学举行2025级本科生开学典礼",
    "publishDate": "2025-09-10",
    "readCount": 14000,
    "likeCount": 256
  },
  {
    "accountId": "njnu-main",
    "title": "乘风破浪求真知！南京师范大学举行2025级研究生开学典礼",
    "publishDate": "2025-09-10",
    "readCount": 7705,
    "likeCount": 108
  },
  {
    "accountId": "njnu-main",
    "title": "致敬大先生！南师大校史上教育家著作展举行",
    "publishDate": "2025-09-09",
    "readCount": 6290,
    "likeCount": 119
  },
  {
    "accountId": "njnu-main",
    "title": "榜样！南师这10位教师获第十四届\"弘爱精英教师奖\"",
    "publishDate": "2025-09-08",
    "readCount": 12000,
    "likeCount": 107
  },
  {
    "accountId": "njnu-main",
    "title": "标杆！南师这10位教师获2025年度\"立德树人奖教金\"",
    "publishDate": "2025-09-08",
    "readCount": 6657,
    "likeCount": 47
  },
  {
    "accountId": "njnu-main",
    "title": "欢迎你，南师新同学！",
    "publishDate": "2025-09-06",
    "readCount": 28000,
    "likeCount": 369
  },
  {
    "accountId": "njnu-main",
    "title": "连续四批，全国高校黄大年式教师团队+1",
    "publishDate": "2025-09-05",
    "readCount": 8597,
    "likeCount": 73
  },
  {
    "accountId": "njnu-main",
    "title": "就在明天，南师新生报到须知",
    "publishDate": "2025-09-05",
    "readCount": 8690,
    "likeCount": 107
  },
  {
    "accountId": "njnu-main",
    "title": "南师举行多种活动纪念抗战胜利80周年",
    "publishDate": "2025-09-04",
    "readCount": 6218,
    "likeCount": 84
  },
  {
    "accountId": "njnu-main",
    "title": "荣耀！九三阅兵现场观礼的南师人",
    "publishDate": "2025-09-03",
    "readCount": 76000,
    "likeCount": 1350
  },
  {
    "accountId": "njnu-main",
    "title": "开学啦！校领导检查新学期第一课",
    "publishDate": "2025-09-02",
    "readCount": 19000,
    "likeCount": 108
  },
  {
    "accountId": "njnu-main",
    "title": "这场特展，在南师开幕！",
    "publishDate": "2025-09-01",
    "readCount": 8036,
    "likeCount": 73
  },
  {
    "accountId": "njnu-main",
    "title": "南师2025级研究生新生数据大揭秘！",
    "publishDate": "2025-08-31",
    "readCount": 28000,
    "likeCount": 495
  },
  {
    "accountId": "njnu-main",
    "title": "南师2025级本科新生数据大揭秘！",
    "publishDate": "2025-08-30",
    "readCount": 31000,
    "likeCount": 519
  },
  {
    "accountId": "njnu-main",
    "title": "董瑶迪：\"无名小卒\"的逆袭之路",
    "publishDate": "2025-08-28",
    "readCount": 14000,
    "likeCount": 177
  },
  {
    "accountId": "njnu-main",
    "title": "暑期，南师学子在一线",
    "publishDate": "2025-08-27",
    "readCount": 8533,
    "likeCount": 75
  },
  {
    "accountId": "njnu-main",
    "title": "一张书桌，一方天地",
    "publishDate": "2025-08-26",
    "readCount": 6922,
    "likeCount": 100
  },
  {
    "accountId": "njnu-main",
    "title": "《人民日报》为南师学子点赞！",
    "publishDate": "2025-08-25",
    "readCount": 18000,
    "likeCount": 195
  },
  {
    "accountId": "njnu-main",
    "title": "《学习时报》刊发校长华桂宏署名文章：提升教育供给与人才需求匹配度",
    "publishDate": "2025-08-24",
    "readCount": 3593,
    "likeCount": 60
  },
  {
    "accountId": "njnu-main",
    "title": "南师大\"十五五\"怎么干？您的建议是······",
    "publishDate": "2025-08-23",
    "readCount": 6440,
    "likeCount": 40
  },
  {
    "accountId": "njnu-main",
    "title": "如何科学谋划\"十五五\"？这场会议擘画发展蓝图",
    "publishDate": "2025-08-22",
    "readCount": 3582,
    "likeCount": 47
  },
  {
    "accountId": "njnu-main",
    "title": "🥇4🥈3🥉5 祝贺!",
    "publishDate": "2025-08-19",
    "readCount": 25000,
    "likeCount": 172
  },
  {
    "accountId": "njnu-main",
    "title": "高雅馨：从\"心\"出发，青春不设限",
    "publishDate": "2025-08-18",
    "readCount": 28000,
    "likeCount": 192
  },
  {
    "accountId": "njnu-main",
    "title": "南师大 ⇌ 伊犁州，开启教育战略新合作",
    "publishDate": "2025-08-16",
    "readCount": 6439,
    "likeCount": 40
  },
  {
    "accountId": "njnu-main",
    "title": "你好，新同学！我们是2025级研究生辅导员!",
    "publishDate": "2025-08-15",
    "readCount": 19000,
    "likeCount": 134
  },
  {
    "accountId": "njnu-main",
    "title": "你好，新同学！我们是2025级本科生辅导员!",
    "publishDate": "2025-08-14",
    "readCount": 44000,
    "likeCount": 335
  },
  {
    "accountId": "njnu-main",
    "title": "独立\"PI\"+专属平台｜南京师范大学海外优青线上宣讲会报名开启",
    "publishDate": "2025-08-13",
    "readCount": 6016,
    "likeCount": 53
  },
  {
    "accountId": "njnu-main",
    "title": "直播预告：南师音乐党课入选文旅部主题展演",
    "publishDate": "2025-08-12",
    "readCount": 2485,
    "likeCount": 49
  },
  {
    "accountId": "njnu-main",
    "title": "沈慧：丈量乡土中国，书写不悔青春",
    "publishDate": "2025-08-11",
    "readCount": 10000,
    "likeCount": 99
  },
  {
    "accountId": "njnu-main",
    "title": "黄和院士受邀在Nature作专题介绍",
    "publishDate": "2025-08-10",
    "readCount": 13000,
    "likeCount": 137
  },
  {
    "accountId": "njnu-main",
    "title": "暑期很热，NNUers更\"燃\"！",
    "publishDate": "2025-08-09",
    "readCount": 7147,
    "likeCount": 86
  },
  {
    "accountId": "njnu-main",
    "title": "校长华桂宏率团赴澳大利亚、马来西亚开展人才招引和校际交流活动",
    "publishDate": "2025-08-07",
    "readCount": 12000,
    "likeCount": 119
  },
  {
    "accountId": "njnu-main",
    "title": "南京师范大学2026年推免生接收预报名的通知",
    "publishDate": "2025-08-06",
    "readCount": 43000,
    "likeCount": 177
  },
  {
    "accountId": "njnu-main",
    "title": "陆婧一：在探索中不断成长",
    "publishDate": "2025-08-04",
    "readCount": 15000,
    "likeCount": 148
  },
  {
    "accountId": "njnu-main",
    "title": "优渥薪酬 全面支持｜最好南师诚邀海外英才依托申报海外优青项目（新增批次）",
    "publishDate": "2025-08-01",
    "readCount": 8378,
    "likeCount": 54
  },
  {
    "accountId": "njnu-main",
    "title": "相聚南师，共谋中非教育合作新篇章！",
    "publishDate": "2025-07-31",
    "readCount": 8536,
    "likeCount": 66
  },
  {
    "accountId": "njnu-main",
    "title": "PNAS+1，南师硕士一作",
    "publishDate": "2025-07-30",
    "readCount": 10000,
    "likeCount": 62
  },
  {
    "accountId": "njnu-main",
    "title": "@南师学子，如遇突发灾害可申请临时困难补助！",
    "publishDate": "2025-07-29",
    "readCount": 3799,
    "likeCount": 59
  },
  {
    "accountId": "njnu-main",
    "title": "吹过南师的风，清凉一夏",
    "publishDate": "2025-07-27",
    "readCount": 12000,
    "likeCount": 128
  },
  {
    "accountId": "njnu-main",
    "title": "学界大咖云集南师，共启思想盛宴!",
    "publishDate": "2025-07-25",
    "readCount": 12000,
    "likeCount": 85
  },
  {
    "accountId": "njnu-main",
    "title": "@2025级NNUer，你的录取通知书正在派送中",
    "publishDate": "2025-07-24",
    "readCount": 18000,
    "likeCount": 234
  },
  {
    "accountId": "njnu-main",
    "title": "央视《大师列传》｜南师资深教授尉天池：观海听涛",
    "publishDate": "2025-07-23",
    "readCount": 5391,
    "likeCount": 78
  },
  {
    "accountId": "njnu-main",
    "title": "南师这堂党课不一般，在京巡演超燃！",
    "publishDate": "2025-07-21",
    "readCount": 5626,
    "likeCount": 83
  },
  {
    "accountId": "njnu-main",
    "title": "南师大2025年本科招生录取阅档工作会议召开",
    "publishDate": "2025-07-19",
    "readCount": 19000,
    "likeCount": 177
  },
  {
    "accountId": "njnu-main",
    "title": "澳洲站｜南京师范大学2025全球人才推介会",
    "publishDate": "2025-07-18",
    "readCount": 10000,
    "likeCount": 55
  },
  {
    "accountId": "njnu-main",
    "title": "无惧\"烤\"验，奋战当\"夏\"！致敬高温下坚守一线的南师人",
    "publishDate": "2025-07-17",
    "readCount": 9459,
    "likeCount": 89
  },
  {
    "accountId": "njnu-main",
    "title": "《中国社会科学报》刊发校党委书记王成斌署名文章：开创新时代思政教育新局面",
    "publishDate": "2025-07-15",
    "readCount": 3863,
    "likeCount": 38
  },
  {
    "accountId": "njnu-main",
    "title": "南京师范大学附属淮安医院揭牌！",
    "publishDate": "2025-07-14",
    "readCount": 17000,
    "likeCount": 99
  },
  {
    "accountId": "njnu-main",
    "title": "闪耀\"苏超\"的南师啦啦操队，飒！",
    "publishDate": "2025-07-12",
    "readCount": 27000,
    "likeCount": 374
  },
  {
    "accountId": "njnu-main",
    "title": "南师大学科建设推进会召开",
    "publishDate": "2025-07-10",
    "readCount": 7170,
    "likeCount": 49
  },
  {
    "accountId": "njnu-main",
    "title": "当科学和文学相遇，会擦出怎样的火花？",
    "publishDate": "2025-07-08",
    "readCount": 4256,
    "likeCount": 54
  },
  {
    "accountId": "njnu-main",
    "title": "张舒彦：AI时代的设计坚守者",
    "publishDate": "2025-07-06",
    "readCount": 14000,
    "likeCount": 152
  },
  {
    "accountId": "njnu-main",
    "title": "祖国的需要，就是南师青年的选择！",
    "publishDate": "2025-07-04",
    "readCount": 7443,
    "likeCount": 162
  },
  {
    "accountId": "njnu-main",
    "title": "南师暑假服务指南，请查收！",
    "publishDate": "2025-07-03",
    "readCount": 21000,
    "likeCount": 132
  },
  {
    "accountId": "njnu-main",
    "title": "认准代码1108，我在南师等你！",
    "publishDate": "2025-07-02",
    "readCount": 16000,
    "likeCount": 257
  },
  {
    "accountId": "njnu-main",
    "title": "南京师范大学+昆士兰大学，双学位！",
    "publishDate": "2025-07-01",
    "readCount": 23000,
    "likeCount": 107
  },
  {
    "accountId": "njnu-main",
    "title": "南师新工科，新专业+1！",
    "publishDate": "2025-06-30",
    "readCount": 22000,
    "likeCount": 109
  },
  {
    "accountId": "njnu-main",
    "title": "南师大+中科院，这个班配置拉满！",
    "publishDate": "2025-06-29",
    "readCount": 33000,
    "likeCount": 171
  },
  {
    "accountId": "njnu-main",
    "title": "首次招生！南师\"欧阳平凯班\"欢迎你填报！",
    "publishDate": "2025-06-28",
    "readCount": 24000,
    "likeCount": 137
  },
  {
    "accountId": "njnu-main",
    "title": "南师新专业！用科技\"复活\"千年文明！",
    "publishDate": "2025-06-27",
    "readCount": 17000,
    "likeCount": 183
  },
  {
    "accountId": "njnu-main",
    "title": "出分了！南师这个新专业，冲！",
    "publishDate": "2025-06-26",
    "readCount": 90000,
    "likeCount": 315
  },
  {
    "accountId": "njnu-main",
    "title": "南京师范大学2025年招生咨询联系方式发布！",
    "publishDate": "2025-06-25",
    "readCount": 18000,
    "likeCount": 119
  },
  {
    "accountId": "njnu-main",
    "title": "来南师，成为这个学院首届学生！",
    "publishDate": "2025-06-25",
    "readCount": 38000,
    "likeCount": 120
  },
  {
    "accountId": "njnu-main",
    "title": "多少分可以上南师？最新报考指南来啦！",
    "publishDate": "2025-06-24",
    "readCount": 81000,
    "likeCount": 760
  },
  {
    "accountId": "njnu-main",
    "title": "毕业心语｜\"师\"情\"话\"意，纸短情长",
    "publishDate": "2025-06-23",
    "readCount": 9297,
    "likeCount": 113
  },
  {
    "accountId": "njnu-main",
    "title": "打完比赛赶高铁上课，这位踢苏超的南师学子太狠了！",
    "publishDate": "2025-06-22",
    "readCount": 43000,
    "likeCount": 549
  },
  {
    "accountId": "njnu-main",
    "title": "南师国际化办学，开启新征程！",
    "publishDate": "2025-06-20",
    "readCount": 11000,
    "likeCount": 85
  },
  {
    "accountId": "njnu-main",
    "title": "未来不设限｜南师2025年本科生毕业典礼暨学位授予仪式隆重举行",
    "publishDate": "2025-06-19",
    "readCount": 12000,
    "likeCount": 259
  },
  {
    "accountId": "njnu-main",
    "title": "时光正好赴新程｜南师2025年研究生毕业典礼暨学位授予仪式隆重举行",
    "publishDate": "2025-06-19",
    "readCount": 7063,
    "likeCount": 120
  },
  {
    "accountId": "njnu-main",
    "title": "今天，南师邀您共赴2025年毕业典礼！",
    "publishDate": "2025-06-18",
    "readCount": 21000,
    "likeCount": 469
  },
  {
    "accountId": "njnu-main",
    "title": "仲靖烨：非典型文科生的自我成长",
    "publishDate": "2025-06-17",
    "readCount": 15000,
    "likeCount": 193
  },
  {
    "accountId": "njnu-main",
    "title": "毕业心语丨那些美好和遗憾",
    "publishDate": "2025-06-16",
    "readCount": 13000,
    "likeCount": 473
  },
  {
    "accountId": "njnu-main",
    "title": "南师大综合评价暨校园开放日工作安排",
    "publishDate": "2025-06-14",
    "readCount": 17000,
    "likeCount": 170
  },
  {
    "accountId": "njnu-main",
    "title": "毕业心语丨我想对你说......",
    "publishDate": "2025-06-13",
    "readCount": 7102,
    "likeCount": 128
  },
  {
    "accountId": "njnu-main",
    "title": "荧光音乐会，如\"乐\"而至【互动有礼】",
    "publishDate": "2025-06-12",
    "readCount": 5870,
    "likeCount": 96
  },
  {
    "accountId": "njnu-main",
    "title": "周子寒：通见光，追逐光，成为光",
    "publishDate": "2025-06-11",
    "readCount": 28000,
    "likeCount": 213
  },
  {
    "accountId": "njnu-main",
    "title": "第26届南师十佳歌手，诞生！",
    "publishDate": "2025-06-10",
    "readCount": 24000,
    "likeCount": 147
  },
  {
    "accountId": "njnu-main",
    "title": "国际档案日丨百年前师范学堂的毕业文凭长啥样？",
    "publishDate": "2025-06-09",
    "readCount": 2916,
    "likeCount": 50
  },
  {
    "accountId": "njnu-main",
    "title": "吴为山、郦波、惠若琪，邀你共赴青春之约",
    "publishDate": "2025-06-07",
    "readCount": 20000,
    "likeCount": 234
  },
  {
    "accountId": "njnu-main",
    "title": "南师女排，三连冠！",
    "publishDate": "2025-06-06",
    "readCount": 8316,
    "likeCount": 340
  },
  {
    "accountId": "njnu-main",
    "title": "下午四点，巅峰对决！",
    "publishDate": "2025-06-05",
    "readCount": 14000,
    "likeCount": 249
  },
  {
    "accountId": "njnu-main",
    "title": "高考倒计时｜这次，轮到你了！",
    "publishDate": "2025-06-04",
    "readCount": 8153,
    "likeCount": 150
  },
  {
    "accountId": "njnu-main",
    "title": "郑日可：逐光而行的音乐织梦人",
    "publishDate": "2025-06-03",
    "readCount": 10000,
    "likeCount": 116
  },
  {
    "accountId": "njnu-main",
    "title": "我是小孩，我同意在南师……",
    "publishDate": "2025-06-01",
    "readCount": 30000,
    "likeCount": 181
  },
  {
    "accountId": "njnu-main",
    "title": "当《随园食单》邂逅端午",
    "publishDate": "2025-05-31",
    "readCount": 4964,
    "likeCount": 69
  },
  {
    "accountId": "njnu-main",
    "title": "NNU草地艺术节｜毕业季，青春当歌！",
    "publishDate": "2025-05-30",
    "readCount": 14000,
    "likeCount": 163
  },
  {
    "accountId": "njnu-main",
    "title": "摆脱手机依赖，拥抱\"无屏\"青春",
    "publishDate": "2025-05-29",
    "readCount": 8724,
    "likeCount": 134
  },
  {
    "accountId": "njnu-main",
    "title": "丁唐婧: 实验室里的追光者",
    "publishDate": "2025-05-28",
    "readCount": 6490,
    "likeCount": 82
  },
  {
    "accountId": "njnu-main",
    "title": "南京师范大学与国家气候中心，携手推进全国重点实验室建设！",
    "publishDate": "2025-05-27",
    "readCount": 5262,
    "likeCount": 78
  },
  {
    "accountId": "njnu-main",
    "title": "科技盛宴，南师启幕！",
    "publishDate": "2025-05-26",
    "readCount": 3694,
    "likeCount": 44
  },
  {
    "accountId": "njnu-main",
    "title": "这份宣言，关乎学生心理健康",
    "publishDate": "2025-05-25",
    "readCount": 4801,
    "likeCount": 59
  },
  {
    "accountId": "njnu-main",
    "title": "校党委书记王成斌率团赴法国、德国开展人才招引和校际交流活动",
    "publishDate": "2025-05-23",
    "readCount": 9003,
    "likeCount": 66
  },
  {
    "accountId": "njnu-main",
    "title": "\"嗨，你想亲自动手做科学实验吗？\"",
    "publishDate": "2025-05-22",
    "readCount": 2647,
    "likeCount": 52
  },
  {
    "accountId": "njnu-main",
    "title": "杜菲：非一般的科研进阶路",
    "publishDate": "2025-05-21",
    "readCount": 10000,
    "likeCount": 100
  },
  {
    "accountId": "njnu-main",
    "title": "夏日校园，打开\"520\"的盲盒",
    "publishDate": "2025-05-20",
    "readCount": 7032,
    "likeCount": 133
  },
  {
    "accountId": "njnu-main",
    "title": "《光明日报》整版刊发——《鲁洁：以生命谱写有品格的教育学》",
    "publishDate": "2025-05-19",
    "readCount": 5629,
    "likeCount": 96
  },
  {
    "accountId": "njnu-main",
    "title": "陈玲杰：从\"学前\"走向\"特教\"",
    "publishDate": "2025-05-18",
    "readCount": 18000,
    "likeCount": 168
  },
  {
    "accountId": "njnu-main",
    "title": "早八倒计时，南师的他们在干什么?",
    "publishDate": "2025-05-16",
    "readCount": 14000,
    "likeCount": 178
  },
  {
    "accountId": "njnu-main",
    "title": "陆杨：从\"问山少年\"到\"点灯人\"的攀援之路",
    "publishDate": "2025-05-15",
    "readCount": 3282,
    "likeCount": 47
  },
  {
    "accountId": "njnu-main",
    "title": "南京师范大学2025年本科生招生章程",
    "publishDate": "2025-05-14",
    "readCount": 24000,
    "likeCount": 140
  },
  {
    "accountId": "njnu-main",
    "title": "毕业答辩，过！过！过！",
    "publishDate": "2025-05-13",
    "readCount": 13000,
    "likeCount": 211
  },
  {
    "accountId": "njnu-main",
    "title": "南师大食品与制药工程学院与工业生物催化教育部重点实验室（清华大学）共建……",
    "publishDate": "2025-05-12",
    "readCount": 8383,
    "likeCount": 66
  },
  {
    "accountId": "njnu-main",
    "title": "NNUTC，用爱点亮梦想",
    "publishDate": "2025-05-11",
    "readCount": 5989,
    "likeCount": 94
  },
  {
    "accountId": "njnu-main",
    "title": "张琨若：跃入旷野，拓展无限可能",
    "publishDate": "2025-05-09",
    "readCount": 17000,
    "likeCount": 209
  },
  {
    "accountId": "njnu-main",
    "title": "为何选择报考南师？\"校友天团\"这么说……",
    "publishDate": "2025-05-08",
    "readCount": 14000,
    "likeCount": 173
  },
  {
    "accountId": "njnu-main",
    "title": "李想：用\"种子哲学\"在南师书写成长传奇",
    "publishDate": "2025-05-07",
    "readCount": 9294,
    "likeCount": 101
  },
  {
    "accountId": "njnu-main",
    "title": "院士引领，全球金奖，我们是南师生物工程 2203 班",
    "publishDate": "2025-05-06",
    "readCount": 8338,
    "likeCount": 81
  },
  {
    "accountId": "njnu-main",
    "title": "祝贺！南师教师惠若琪获新时代青年先锋奖",
    "publishDate": "2025-05-04",
    "readCount": 17000,
    "likeCount": 180
  },
  {
    "accountId": "njnu-main",
    "title": "南师骄傲！龚翔宇任中国女排队长",
    "publishDate": "2025-05-03",
    "readCount": 14000,
    "likeCount": 293
  },
  {
    "accountId": "njnu-main",
    "title": "法国、德国站丨南京师范大学2025全球人才推介会",
    "publishDate": "2025-05-02",
    "readCount": 8615,
    "likeCount": 60
  },
  {
    "accountId": "njnu-main",
    "title": "五一，为南师劳动者喝彩！",
    "publishDate": "2025-05-01",
    "readCount": 3726,
    "likeCount": 114
  },
  {
    "accountId": "njnu-main",
    "title": "南京师范大学2025年综合评价招生简章",
    "publishDate": "2025-04-30",
    "readCount": 20000,
    "likeCount": 80
  },
  {
    "accountId": "njnu-main",
    "title": "南京师范大学与南宁市人民政府，签约！",
    "publishDate": "2025-04-29",
    "readCount": 11000,
    "likeCount": 82
  },
  {
    "accountId": "njnu-main",
    "title": "熊韵涵：跨学科科研的破茧成蝶之路",
    "publishDate": "2025-04-28",
    "readCount": 24000,
    "likeCount": 185
  },
  {
    "accountId": "njnu-main",
    "title": "趣动南师，嗨翻全场！",
    "publishDate": "2025-04-27",
    "readCount": 10000,
    "likeCount": 74
  },
  {
    "accountId": "njnu-main",
    "title": "别宅啦！NNUer春日运动大放送",
    "publishDate": "2025-04-25",
    "readCount": 8505,
    "likeCount": 72
  },
  {
    "accountId": "njnu-main",
    "title": "阮玉欣：在南师留学的越南姑娘",
    "publishDate": "2025-04-24",
    "readCount": 33000,
    "likeCount": 250
  },
  {
    "accountId": "njnu-main",
    "title": "一起读书吧，不止今天",
    "publishDate": "2025-04-23",
    "readCount": 2621,
    "likeCount": 49
  },
  {
    "accountId": "njnu-main",
    "title": "春风拂过，南师邀你赏花",
    "publishDate": "2025-04-22",
    "readCount": 6906,
    "likeCount": 115
  },
  {
    "accountId": "njnu-main",
    "title": "洪秀柱在南京师范大学发表演讲",
    "publishDate": "2025-04-19",
    "readCount": 61000,
    "likeCount": 929
  },
  {
    "accountId": "njnu-main",
    "title": "高考倒计时50天｜南师大校长华桂宏为考生加油！",
    "publishDate": "2025-04-18",
    "readCount": 5947,
    "likeCount": 117
  },
  {
    "accountId": "njnu-main",
    "title": "《人民日报》刊发校党委书记王成斌署名文章：把科技人才\"送\"到企业创新一线",
    "publishDate": "2025-04-17",
    "readCount": 6468,
    "likeCount": 66
  },
  {
    "accountId": "njnu-main",
    "title": "上新了！看看NNUers的春日焕新清单",
    "publishDate": "2025-04-16",
    "readCount": 7110,
    "likeCount": 96
  },
  {
    "accountId": "njnu-main",
    "title": "周龙：在南师，绘就\"多面\"精彩",
    "publishDate": "2025-04-15",
    "readCount": 8732,
    "likeCount": 114
  },
  {
    "accountId": "njnu-main",
    "title": "人民日报海外版：在泥蜂舍 编虫子书",
    "publishDate": "2025-04-14",
    "readCount": 4763,
    "likeCount": 71
  },
  {
    "accountId": "njnu-main",
    "title": "祝贺！南师3位学子入选！",
    "publishDate": "2025-04-12",
    "readCount": 33000,
    "likeCount": 241
  },
  {
    "accountId": "njnu-main",
    "title": "重要提醒！4月12日起，这些道路临时管控→（内附交通绕行示意图）",
    "publishDate": "2025-04-12",
    "readCount": 3713,
    "likeCount": 8
  },
  {
    "accountId": "njnu-main",
    "title": "南京师范大学2025年高校专项计划招生简章（厂生计划）",
    "publishDate": "2025-04-11",
    "readCount": 15000,
    "likeCount": 50
  },
  {
    "accountId": "njnu-main",
    "title": "当青春遇见\"L\"\"A\"\"W\"",
    "publishDate": "2025-04-10",
    "readCount": 5580,
    "likeCount": 49
  },
  {
    "accountId": "njnu-main",
    "title": "0→10000000，校园方寸→国际万象",
    "publishDate": "2025-04-09",
    "readCount": 9697,
    "likeCount": 100
  },
  {
    "accountId": "njnu-main",
    "title": "南师校园里的春和景明，一起打卡！",
    "publishDate": "2025-04-08",
    "readCount": 11000,
    "likeCount": 162
  },
  {
    "accountId": "njnu-main",
    "title": "春日当奋进，南师学子\"最美\"作息表看过来！",
    "publishDate": "2025-04-07",
    "readCount": 10000,
    "likeCount": 106
  },
  {
    "accountId": "njnu-main",
    "title": "丁一宸：做飞向田野的漆园蝶",
    "publishDate": "2025-04-06",
    "readCount": 30000,
    "likeCount": 360
  },
  {
    "accountId": "njnu-main",
    "title": "今天，送您一朵小白花",
    "publishDate": "2025-04-04",
    "readCount": 10000,
    "likeCount": 183
  },
  {
    "accountId": "njnu-main",
    "title": "何以\"十佳\"？2204班的答案是......",
    "publishDate": "2025-04-03",
    "readCount": 9524,
    "likeCount": 70
  },
  {
    "accountId": "njnu-main",
    "title": "《胜利之歌——歌声里的新四军》音乐党课正式展演",
    "publishDate": "2025-04-02",
    "readCount": 2903,
    "likeCount": 52
  },
  {
    "accountId": "njnu-main",
    "title": "第二十届中国青少年发展论坛在南京师范大学举办",
    "publishDate": "2025-04-01",
    "readCount": 7801,
    "likeCount": 75
  },
  {
    "accountId": "njnu-main",
    "title": "南师赠予我的，是___",
    "publishDate": "2025-03-31",
    "readCount": 9697,
    "likeCount": 122
  },
  {
    "accountId": "njnu-main",
    "title": "高考倒计时70天，南师的春天等你来见",
    "publishDate": "2025-03-29",
    "readCount": 6929,
    "likeCount": 147
  },
  {
    "accountId": "njnu-main",
    "title": "编号000001！三张\"绝版\"证件后藏着怎样的故事？",
    "publishDate": "2025-03-28",
    "readCount": 13000,
    "likeCount": 160
  },
  {
    "accountId": "njnu-main",
    "title": "南京师范大学⇌田家炳基金会，首个AI赋能教育项目启动",
    "publishDate": "2025-03-27",
    "readCount": 6012,
    "likeCount": 61
  },
  {
    "accountId": "njnu-main",
    "title": "联合国讲台上的南师声音",
    "publishDate": "2025-03-26",
    "readCount": 30000,
    "likeCount": 556
  },
  {
    "accountId": "njnu-main",
    "title": "就在明天！1W+岗位等你来",
    "publishDate": "2025-03-25",
    "readCount": 15000,
    "likeCount": 90
  },
  {
    "accountId": "njnu-main",
    "title": "2025年南京师范大学硕士研究生招生复试和录取工作实施办法",
    "publishDate": "2025-03-24",
    "readCount": 23000,
    "likeCount": 104
  },
  {
    "accountId": "njnu-main",
    "title": "南师，蝉联第一等次！",
    "publishDate": "2025-03-22",
    "readCount": 17000,
    "likeCount": 131
  },
  {
    "accountId": "njnu-main",
    "title": "南京师范大学2025年硕士研究生招生复试分数线公布！",
    "publishDate": "2025-03-22",
    "readCount": 23000,
    "likeCount": 113
  },
  {
    "accountId": "njnu-main",
    "title": "春风起，南师的玉兰花开了~",
    "publishDate": "2025-03-21",
    "readCount": 17000,
    "likeCount": 353
  },
  {
    "accountId": "njnu-main",
    "title": "他们的青春这样发光！",
    "publishDate": "2025-03-20",
    "readCount": 7413,
    "likeCount": 76
  },
  {
    "accountId": "njnu-main",
    "title": "南师大\"院士林\"，落成！",
    "publishDate": "2025-03-19",
    "readCount": 19000,
    "likeCount": 136
  },
  {
    "accountId": "njnu-main",
    "title": "南京师范大学召开传达学习2025年全国两会精神报告会",
    "publishDate": "2025-03-18",
    "readCount": 3107,
    "likeCount": 26
  },
  {
    "accountId": "njnu-main",
    "title": "省委第三巡视组向南京师范大学党委反馈巡视情况",
    "publishDate": "2025-03-18",
    "readCount": 7277,
    "likeCount": 22
  },
  {
    "accountId": "njnu-main",
    "title": "高福院士，南师开讲！",
    "publishDate": "2025-03-17",
    "readCount": 13000,
    "likeCount": 91
  },
  {
    "accountId": "njnu-main",
    "title": "强强联手！南京师范大学 & 山东大学，共建全国重点实验室！",
    "publishDate": "2025-03-16",
    "readCount": 28000,
    "likeCount": 1353
  },
  {
    "accountId": "njnu-main",
    "title": "江来：以体育之名，书写热血与仁爱的青春答卷",
    "publishDate": "2025-03-14",
    "readCount": 18000,
    "likeCount": 529
  },
  {
    "accountId": "njnu-main",
    "title": "祝贺！南师大5项入选",
    "publishDate": "2025-03-13",
    "readCount": 23000,
    "likeCount": 256
  },
  {
    "accountId": "njnu-main",
    "title": "春日南师，每一步都算\"树\"",
    "publishDate": "2025-03-12",
    "readCount": 7157,
    "likeCount": 194
  },
  {
    "accountId": "njnu-main",
    "title": "首届本科学子 → 十佳示范班级",
    "publishDate": "2025-03-11",
    "readCount": 12000,
    "likeCount": 177
  },
  {
    "accountId": "njnu-main",
    "title": "嘿！三月的南师按下了播放键▶",
    "publishDate": "2025-03-10",
    "readCount": 23000,
    "likeCount": 303
  },
  {
    "accountId": "njnu-main",
    "title": "点赞！南师\"她力量\"",
    "publishDate": "2025-03-08",
    "readCount": 11000,
    "likeCount": 351
  },
  {
    "accountId": "njnu-main",
    "title": "2025南京师范大学对外合作指引，上线！",
    "publishDate": "2025-03-07",
    "readCount": 13000,
    "likeCount": 747
  },
  {
    "accountId": "njnu-main",
    "title": "凝心聚\"能\"，南师这个班动力无限！",
    "publishDate": "2025-03-06",
    "readCount": 7129,
    "likeCount": 55
  },
  {
    "accountId": "njnu-main",
    "title": "我们，与雷锋精神同行！",
    "publishDate": "2025-03-05",
    "readCount": 3870,
    "likeCount": 52
  },
  {
    "accountId": "njnu-main",
    "title": "从\"倒数第二\"到\"正数第一\"，她是如何做到的?",
    "publishDate": "2025-03-04",
    "readCount": 37000,
    "likeCount": 410
  },
  {
    "accountId": "njnu-main",
    "title": "通通上岸！南师2025升学就业月历来啦",
    "publishDate": "2025-03-03",
    "readCount": 16000,
    "likeCount": 195
  },
  {
    "accountId": "njnu-main",
    "title": "倒计时1天｜2025国际青年学者论坛即将开幕",
    "publishDate": "2025-03-02",
    "readCount": 4530,
    "likeCount": 32
  },
  {
    "accountId": "njnu-main",
    "title": "南京师范大学2025年专业技术人员招聘公告",
    "publishDate": "2025-03-02",
    "readCount": 11000,
    "likeCount": 14
  },
  {
    "accountId": "njnu-main",
    "title": "逐梦光影，青春\"镜\"当时！",
    "publishDate": "2025-02-28",
    "readCount": 6167,
    "likeCount": 65
  },
  {
    "accountId": "njnu-main",
    "title": "赛场🟦课堂，这个\"冠军型班级\"如何双赢？",
    "publishDate": "2025-02-27",
    "readCount": 6370,
    "likeCount": 46
  },
  {
    "accountId": "njnu-main",
    "title": "南师这个班，多个100%！",
    "publishDate": "2025-02-26",
    "readCount": 24000,
    "likeCount": 163
  },
  {
    "accountId": "njnu-main",
    "title": "我在南师，等你上岸！",
    "publishDate": "2025-02-24",
    "readCount": 29000,
    "likeCount": 315
  },
  {
    "accountId": "njnu-main",
    "title": "南师大2025年硕士研究生招生考试初试成绩即将公布！",
    "publishDate": "2025-02-23",
    "readCount": 31000,
    "likeCount": 210
  },
  {
    "accountId": "njnu-main",
    "title": "什么？南师课题组发现的新物种叫\"苏轼无爪螈\"！😊",
    "publishDate": "2025-02-21",
    "readCount": 7503,
    "likeCount": 121
  },
  {
    "accountId": "njnu-main",
    "title": "当我问DeepSeek：\"在南师就读是怎样一种体验？\"",
    "publishDate": "2025-02-20",
    "readCount": 22000,
    "likeCount": 207
  },
  {
    "accountId": "njnu-main",
    "title": "南师这个班，能量满满！",
    "publishDate": "2025-02-19",
    "readCount": 15000,
    "likeCount": 97
  },
  {
    "accountId": "njnu-main",
    "title": "曾嫣：从南师走出的\"水果女王\"",
    "publishDate": "2025-02-18",
    "readCount": 52000,
    "likeCount": 307
  },
  {
    "accountId": "njnu-main",
    "title": "新学期起航！南师专属计划表等你来领",
    "publishDate": "2025-02-17",
    "readCount": 9048,
    "likeCount": 181
  },
  {
    "accountId": "njnu-main",
    "title": "2025年，南师这么干！",
    "publishDate": "2025-02-16",
    "readCount": 15000,
    "likeCount": 84
  },
  {
    "accountId": "njnu-main",
    "title": "南京师范大学2025年\"推进一流大学建设\"研讨会召开",
    "publishDate": "2025-02-14",
    "readCount": 9380,
    "likeCount": 79
  },
  {
    "accountId": "njnu-main",
    "title": "今日元宵！南师祝您事事圆",
    "publishDate": "2025-02-12",
    "readCount": 4410,
    "likeCount": 89
  },
  {
    "accountId": "njnu-main",
    "title": "这个寒假，南师学子的IP在哪里？",
    "publishDate": "2025-02-11",
    "readCount": 7845,
    "likeCount": 75
  },
  {
    "accountId": "njnu-main",
    "title": "在南师，他用50年匠心诠释漆画之美",
    "publishDate": "2025-02-10",
    "readCount": 9573,
    "likeCount": 118
  },
  {
    "accountId": "njnu-main",
    "title": "南师学子镜头下的年味，氛围感拉满！",
    "publishDate": "2025-02-09",
    "readCount": 6599,
    "likeCount": 97
  },
  {
    "accountId": "njnu-main",
    "title": "30颗心，一个信念！",
    "publishDate": "2025-02-07",
    "readCount": 6235,
    "likeCount": 59
  },
  {
    "accountId": "njnu-main",
    "title": "艺术生上岸数学研究生！他的故事充满无限可能！",
    "publishDate": "2025-02-06",
    "readCount": 21000,
    "likeCount": 315
  },
  {
    "accountId": "njnu-main",
    "title": "当剪纸遇上南师，AI了！",
    "publishDate": "2025-02-05",
    "readCount": 6097,
    "likeCount": 149
  },
  {
    "accountId": "njnu-main",
    "title": "新春彩铃，南师赠予你",
    "publishDate": "2025-02-03",
    "readCount": 4063,
    "likeCount": 51
  },
  {
    "accountId": "njnu-main",
    "title": "福气满满！南师红包封面惊喜返场！",
    "publishDate": "2025-02-02",
    "readCount": 11000,
    "likeCount": 163
  },
  {
    "accountId": "njnu-main",
    "title": "南师专属好运来袭，快来解锁！",
    "publishDate": "2025-02-01",
    "readCount": 5488,
    "likeCount": 78
  },
  {
    "accountId": "njnu-main",
    "title": "Xiu~请查收南师专属新年福卡",
    "publishDate": "2025-01-31",
    "readCount": 6054,
    "likeCount": 103
  },
  {
    "accountId": "njnu-main",
    "title": "拜年啦！南师祝您蛇年大吉！",
    "publishDate": "2025-01-29",
    "readCount": 6647,
    "likeCount": 148
  },
  {
    "accountId": "njnu-main",
    "title": "NNUer的年度相册里有什么？",
    "publishDate": "2025-01-28",
    "readCount": 6431,
    "likeCount": 103
  },
  {
    "accountId": "njnu-main",
    "title": "🧧来了！南师专属红包封面限时领！",
    "publishDate": "2025-01-27",
    "readCount": 24000,
    "likeCount": 482
  },
  {
    "accountId": "njnu-main",
    "title": "南京师范大学2025年非教学单位工作人员（人事代理）招聘公告",
    "publishDate": "2025-01-26",
    "readCount": 35000,
    "likeCount": 44
  },
  {
    "accountId": "njnu-main",
    "title": "校领导走访慰问寒假留校学生及在岗教职员工",
    "publishDate": "2025-01-25",
    "readCount": 16000,
    "likeCount": 101
  },
  {
    "accountId": "njnu-main",
    "title": "@全球英才｜南京师范大学国际青年学者论坛开启报名！",
    "publishDate": "2025-01-23",
    "readCount": 8417,
    "likeCount": 40
  },
  {
    "accountId": "njnu-main",
    "title": "\"爸妈，我在南师第一学期挺好的\"",
    "publishDate": "2025-01-21",
    "readCount": 24000,
    "likeCount": 223
  },
  {
    "accountId": "njnu-main",
    "title": "南京师范大学2025年公开招聘专职辅导员公告",
    "publishDate": "2025-01-20",
    "readCount": 50000,
    "likeCount": 108
  },
  {
    "accountId": "njnu-main",
    "title": "央视报道！南师大考古发掘取得重要成果",
    "publishDate": "2025-01-19",
    "readCount": 46000,
    "likeCount": 505
  },
  {
    "accountId": "njnu-main",
    "title": "寒！假！通！知！🔔",
    "publishDate": "2025-01-17",
    "readCount": 36000,
    "likeCount": 124
  },
  {
    "accountId": "njnu-main",
    "title": "寒！假！通！知！",
    "publishDate": "2025-01-17",
    "readCount": 36000,
    "likeCount": 124
  },
  {
    "accountId": "njnu-main",
    "title": "援藏支教→上岸南师→参军入伍，他的人生不设限",
    "publishDate": "2025-01-16",
    "readCount": 11000,
    "likeCount": 145
  },
  {
    "accountId": "njnu-main",
    "title": "致敬！他们在南师光荣退休！",
    "publishDate": "2025-01-15",
    "readCount": 17000,
    "likeCount": 129
  },
  {
    "accountId": "njnu-main",
    "title": "微生物，原来这么有意思？！",
    "publishDate": "2025-01-14",
    "readCount": 6271,
    "likeCount": 184
  },
  {
    "accountId": "njnu-main",
    "title": "祝贺！全部获评\"A等次\"！",
    "publishDate": "2025-01-13",
    "readCount": 30000,
    "likeCount": 138
  },
  {
    "accountId": "njnu-main",
    "title": "王宇轩：且行且思，用奋斗书写卓越教师梦",
    "publishDate": "2025-01-12",
    "readCount": 15000,
    "likeCount": 123
  },
  {
    "accountId": "njnu-main",
    "title": "NNU冬日暖心图鉴，请查收！",
    "publishDate": "2025-01-09",
    "readCount": 11000,
    "likeCount": 125
  },
  {
    "accountId": "njnu-main",
    "title": "紧急通知！南师与你共渡难关！",
    "publishDate": "2025-01-08",
    "readCount": 66000,
    "likeCount": 503
  },
  {
    "accountId": "njnu-main",
    "title": "陈妹宇：乘风破浪，成为\"船长\"的蜕变之旅",
    "publishDate": "2025-01-07",
    "readCount": 9411,
    "likeCount": 81
  },
  {
    "accountId": "njnu-main",
    "title": "打开这篇推文，期末周轻松拿捏！",
    "publishDate": "2025-01-06",
    "readCount": 6963,
    "likeCount": 129
  },
  {
    "accountId": "njnu-main",
    "title": "南师2025月历，带你穿越四季之美",
    "publishDate": "2025-01-05",
    "readCount": 12000,
    "likeCount": 568
  },
  {
    "accountId": "njnu-main",
    "title": "出炉！南师年度图书借阅Top10！",
    "publishDate": "2025-01-03",
    "readCount": 13000,
    "likeCount": 184
  },
  {
    "accountId": "njnu-main",
    "title": "新年快乐！南师给您送\"福\"啦！",
    "publishDate": "2025-01-02",
    "readCount": 6757,
    "likeCount": 109
  }
]